meltingplot/__init__.py
meltingplot/duet_simplyprint_connector/__init__.py
meltingplot/duet_simplyprint_connector/__main__.py
meltingplot/duet_simplyprint_connector/_version.py
meltingplot/duet_simplyprint_connector/gcode.py
meltingplot/duet_simplyprint_connector/network.py
meltingplot/duet_simplyprint_connector/state.py
meltingplot/duet_simplyprint_connector/task.py
meltingplot/duet_simplyprint_connector/virtual_client.py
meltingplot/duet_simplyprint_connector/watchdog.py
meltingplot/duet_simplyprint_connector/webcam.py
meltingplot/duet_simplyprint_connector/cli/__init__.py
meltingplot/duet_simplyprint_connector/cli/autodiscover.py
meltingplot/duet_simplyprint_connector/cli/install.py
meltingplot/duet_simplyprint_connector/duet/__init__.py
meltingplot/duet_simplyprint_connector/duet/api.py
meltingplot/duet_simplyprint_connector/duet/model.py
meltingplot_duet_simplyprint_connector-1.3.10.data/data/simplyprint-connector.service
meltingplot_duet_simplyprint_connector-1.3.10.dist-info/licenses/LICENSE
meltingplot_duet_simplyprint_connector-1.3.10.dist-info/METADATA
meltingplot_duet_simplyprint_connector-1.3.10.dist-info/WHEEL
meltingplot_duet_simplyprint_connector-1.3.10.dist-info/entry_points.txt
meltingplot_duet_simplyprint_connector-1.3.10.dist-info/top_level.txt
meltingplot_duet_simplyprint_connector-1.3.10.dist-info/RECORD
