Metadata-Version: 2.4
Name: meltingplot.duet_simplyprint_connector
Version: 1.3.10
Summary: Simplyprint.io connector for 3D printers running Duet firmware.
Home-page: 
Author: Tim Schneider
Author-email: tim@meltingplot.net
License:                                  Apache License
License-File: LICENSE
Requires-Dist: simplyprint-ws-client==1.0.1rc22
Requires-Dist: aiohttp
Requires-Dist: attrs
Requires-Dist: imageio[ffmpeg]
Requires-Dist: psutil
Requires-Dist: strenum
Requires-Dist: pyee
Provides-Extra: test
Requires-Dist: pytest-cov; extra == "test"
Requires-Dist: pytest-mock; extra == "test"
Requires-Dist: pytest-asyncio; extra == "test"
Requires-Dist: flake8; extra == "test"
Requires-Dist: flake8-import-order==0.18.2; extra == "test"
Requires-Dist: flake8-blind-except; extra == "test"
Requires-Dist: flake8-builtins; extra == "test"
Requires-Dist: flake8-docstrings; extra == "test"
Requires-Dist: flake8-bugbear; extra == "test"
Requires-Dist: flake8-comprehensions; extra == "test"
Requires-Dist: flake8-commas; extra == "test"
Requires-Dist: pep8-naming; extra == "test"
Requires-Dist: bandit; extra == "test"
Requires-Dist: yapf; extra == "test"
Requires-Dist: versioneer; extra == "test"
Dynamic: author
Dynamic: author-email
Dynamic: description
Dynamic: description-content-type
Dynamic: license
Dynamic: license-file
Dynamic: provides-extra
Dynamic: requires-dist
Dynamic: summary
